tlt/__init__.py
tlt/version.py
tlt/components/__init__.py
tlt/components/docker_handler/__init__.py
tlt/components/docker_handler/docker_handler.py
tlt/components/instance_handler/__init__.py
tlt/components/instance_handler/base_instance.py
tlt/components/instance_handler/local_instance.py
tlt/components/instance_handler/utils.py
tlt/components/types/__init__.py
tlt/components/types/task.py
tlt/config/__init__.py
tlt/config/config.json
tlt/entrypoint/__init__.py
tlt/entrypoint/entrypoint.py
tlt/license/EULA.pdf
tlt/license/__init__.py
nvidia_tlt-0.1.21.dist-info/METADATA
nvidia_tlt-0.1.21.dist-info/WHEEL
nvidia_tlt-0.1.21.dist-info/entry_points.txt
nvidia_tlt-0.1.21.dist-info/top_level.txt
nvidia_tlt-0.1.21.dist-info/RECORD
