Metadata-Version: 2.1
Name: nvidia-tlt
Version: 0.1.21
Summary: NVIDIA's Launcher for TAO Toolkit.
Home-page: UNKNOWN
Author: Varun Praveen
Author-email: vpraveen@nvidia.com
License: NVIDIA Proprietary Software
Keywords: nvidia,tao,launcher
Platform: UNKNOWN
Classifier: Intended Audience :: Developers
Classifier: Topic :: Software Development :: Libraries
Classifier: Topic :: Software Development :: Libraries :: Python Modules
Classifier: Environment :: Console
Classifier: License :: Other/Proprietary License
Classifier: Programming Language :: Python :: 3
Classifier: Topic :: Scientific/Engineering :: Artificial Intelligence
Requires-Python: >=3.6.*
Requires-Dist: certifi (==2020.6.20)
Requires-Dist: chardet (==3.0.4)
Requires-Dist: docker (==4.3.1)
Requires-Dist: docker-pycreds (==0.4.0)
Requires-Dist: idna (==2.10)
Requires-Dist: requests (==2.24.0)
Requires-Dist: six (==1.15.0)
Requires-Dist: tabulate (==0.8.7)
Requires-Dist: urllib3 (==1.25.10)
Requires-Dist: websocket-client (==0.57.0)
